[
	{
		"id": 2,
		"name": "Chaim Lewis",
		"email": "dui.in@egetlacus.ca",
		"phone": "(294) 840-6685"
	},
	{
		"id": 3,
		"name": "Kennedy Lane",
		"email": "mattis.Cras@nonenimMauris.net",
		"phone": "(542) 451-7038"
	},
	{
		"id": 4,
		"name": "Wylie Pope",
		"email": "test2@mail.ua",
		"phone": "(692) 802-2949"
	},
	{
		"id": 6,
		"name": "Abbot Franks",
		"email": "scelerisque@magnis.org",
		"phone": "(186) 568-3720"
	},
	{
		"id": 7,
		"name": "Reuben Henry",
		"email": "test2@mail.ua",
		"phone": "(715) 598-5792"
	},
	{
		"id": 9,
		"name": "dfdfdgd",
		"email": "nibh@semsempererat.com",
		"phone": "(704) 000000000"
	},
	{
		"id": 10,
		"name": "Alec Howard",
		"email": "Donec.elementum@scelerisquescelerisquedui.net",
		"phone": "(748) 206-2688"
	},
	{
		"id": "sTz8COsuG",
		"name": "Lisvsdnk",
		"email": "a@mddail.com",
		"phone": "+38501111111"
	},
	{
		"id": "iHD2Dn2dZ",
		"name": "Lisvsdnk",
		"email": "a@mddail.com",
		"phone": "+38501111111"
	},
	{
		"id": "0fLN34v4N",
		"name": "Abbranks",
		"email": "scelerisque@magnis.ua",
		"phone": "(186) 568-3720"
	},
	{
		"id": "xLTPbOxMk",
		"name": "Abbranks",
		"email": "scelerisque@magnis.ua",
		"phone": "(186) 568-3720"
	},
	{
		"id": "QNXaqLYYO",
		"name": "BBB",
		"email": "b@mail.com",
		"phone": "+38501111111"
	},
	{
		"id": "dnqwtnNKc",
		"name": "ddd",
		"email": "d@mail.com",
		"phone": "+38501111111"
	},
	{
		"id": "B9jwnFY7P",
		"name": "ddd",
		"email": "d@mail.com",
		"phone": "+38501111111"
	},
	{
		"id": "_NJpoxbTN",
		"name": "ddd",
		"email": "d@mail.com",
		"phone": "+38501111111"
	},
	{
		"id": "cwmV7p3YM",
		"name": "ddd",
		"email": "d@mail.com",
		"phone": "+38501111111"
	}
]